__init__.py
tiny_emitter.py
tiny_emitter-1.0.0.dist-info/LICENSE
tiny_emitter-1.0.0.dist-info/METADATA
tiny_emitter-1.0.0.dist-info/WHEEL
tiny_emitter-1.0.0.dist-info/top_level.txt
tiny_emitter-1.0.0.dist-info/RECORD
