Metadata-Version: 2.1
Name: tiny-emitter
Version: 1.0.0
Summary: A lightweight event emitter library for Python
Author-email: Felix Korovin <felix.korovin@icloud.com>
License: MIT License        
Project-URL: Homepage, https://github.com/skilef/tiny-emitter
Classifier: Programming Language :: Python :: 3
Classifier: License :: OSI Approved :: MIT License
Classifier: Operating System :: OS Independent
Requires-Python: >=3.7
License-File: LICENSE
